[{"name":"Dillon SP","total":216},{"name":"The Wilds","total":206},{"name":"Dillon SP--Beach and Trails","total":175},{"name":"Dillon Wildlife Area--Pleasant Valley Rd. Access","total":167},{"name":"Tri-Valley Wildlife Area","total":158},{"name":"New Concord Village Reservoir","total":156},{"name":"The Wilds--Zion Ridge Rd.","total":145},{"name":"The Wilds--Birding Station at Jeffrey Point","total":138},{"name":"Dillon Reservoir--Dam","total":134},{"name":"The Wilds--International Rd.","total":132}]