[{"name":"Mosquito Creek Wildlife Area","total":232},{"name":"Mosquito Lake--North End","total":223},{"name":"Mosquito Lake SP","total":206},{"name":"Mosquito Creek Wildlife Area--Hoagland-Blackstub Rd.","total":202},{"name":"Grand River Wildlife Area--Norton Lane Ponds","total":197},{"name":"Mosquito Lake--Lakeview Recreation Area","total":176},{"name":"Mosquito Creek Wildlife Area--Mahan-Denman Boat Launch","total":169},{"name":"Mosquito Lake SP--Turkey Run Trail","total":167},{"name":"Grand River Wildlife Area--Hoffman Norton Rd. South","total":161},{"name":"Mosquito Lake--Causeway","total":158}]