[{"id":"L3898030","name":"Bluffton University Nature Preserve","total":185},{"id":"L809871","name":"Ferguson and Metzger Reservoirs","total":183},{"id":"L809876","name":"Lost Creek Reservoir","total":180},{"id":"L1906430","name":"Kendrick Woods State Nature Preserve","total":161},{"id":"L5045655","name":"Cobb Lake","total":150},{"id":"L3264086","name":"Ottawa Metro Park and Lima Reservoir","total":150},{"id":"L2411215","name":"Williams Reservoir","total":149},{"id":"L294963","name":"Bresler Reservoir","total":139},{"id":"L3054817","name":"Lippincott Bird Sanctuary","total":131},{"id":"L3052101","name":"Tecumseh Nature Preserve","total":118}]