[{"id":"L140466","name":"Hueston Woods SP (Preble Co.)","total":246},{"id":"L500610","name":"Hueston Woods SP--Acton Lake (Preble Co.)","total":214},{"id":"L7126532","name":"Hueston Woods SP--Group Camp","total":212},{"id":"L1627748","name":"Hueston Woods SP--Marina","total":186},{"id":"L8865086","name":"Hueston Woods SP--Beach","total":170},{"id":"L14456310","name":"Hueston Woods SP--Sugar Camp Area and Fishing Pier","total":134},{"id":"L1915583","name":"Woodland Trails Wildlife Area","total":120},{"id":"L12156958","name":"Hueston Woods SP--Big Woods Trail","total":119},{"id":"L1915129","name":"Rush Run Wildlife Area","total":113},{"id":"L3467918","name":"Hueston Woods SP--Lodge","total":111}]